firestore4kivy/__init__.py
firestore4kivy/firestore4kivy.py
firestore4kivy-0.0.1.dist-info/LICENSE
firestore4kivy-0.0.1.dist-info/METADATA
firestore4kivy-0.0.1.dist-info/WHEEL
firestore4kivy-0.0.1.dist-info/top_level.txt
firestore4kivy-0.0.1.dist-info/RECORD
