Metadata-Version: 2.1
Name: firestore4kivy
Version: 0.0.1
Summary: A basic REST Firestore api.
Home-page: https://github.com/Android-for-Python/firestore4kivy
Author: Robert Flatt
Classifier: Intended Audience :: Developers
Classifier: Topic :: Software Development :: Build Tools
Classifier: Programming Language :: Python :: 3
Classifier: License :: OSI Approved :: MIT License
Classifier: Operating System :: OS Independent
Requires-Python: >=3.6
License-File: LICENSE
Requires-Dist: requests
